LICENSE.txt
MANIFEST.in
README.rst
development.pip
development_py26.pip
requirements.pip
requirements_py26.pip
setup.py
kairos/__init__.py
kairos/cassandra_backend.py
kairos/exceptions.py
kairos/mongo_backend.py
kairos/redis_backend.py
kairos/sql_backend.py
kairos/timeseries.py
kairos.egg-info/PKG-INFO
kairos.egg-info/SOURCES.txt
kairos.egg-info/dependency_links.txt
kairos.egg-info/requires.txt
kairos.egg-info/top_level.txt