Metadata-Version: 1.1
Name: kairos
Version: 0.8.1
Summary: Time series data storage in Redis, Mongo, SQL and Cassandra
Home-page: https://github.com/agoragames/kairos
Author: Aaron Westendorf
Author-email: aaron@agoragames.com
License: LICENSE.txt
Keywords: python,redis,mongo,sql,mysql,sqlite,postgresql,cassandra,time,timeseries,rrd,gevent,statistics
Platform: UNKNOWN
Classifier: Development Status :: 3 - Alpha
Classifier: License :: OSI Approved :: BSD License
Classifier: Intended Audience :: Developers
Classifier: Operating System :: POSIX
Classifier: Topic :: Communications
Classifier: Topic :: System :: Distributed Computing
Classifier: Topic :: Software Development :: Libraries :: Python Modules
Classifier: Programming Language :: Python
Classifier: Programming Language :: Python :: 2.7
Classifier: Topic :: Software Development :: Libraries
